{
  "products": [
    {
      "title": "Fone QCY T13 ANC",
      "value": "169,90",
      "situation": "Em aberto",
      "image": "https://qcybrasil.com/cdn/shop/files/01_5c0faa72-c26b-46f8-9748-55b033ae6a53.png?v=1696531599",
      "id": "5bf6"
    },
    {
      "title": "Smartwatch QCY GTC S1",
      "value": "200,00",
      "situation": "Em aberto",
      "image": "https://qcybrasil.com/cdn/shop/files/01_42f49275-5b09-40cc-a56e-fc0f90b12b69.png?v=1696602859",
      "id": "a497"
    },
    {
      "id": "095b",
      "title": "Headset  H3 ANC",
      "value": "250,90",
      "situation": "Pago",
      "image": "https://qcybrasil.com/cdn/shop/files/PRETO_01_a004fb0f-e39a-4ea6-9522-e3b87170e421.png?v=1704486194"
    },
    {
      "id": "8d64",
      "title": "Samsung Galaxy S23",
      "value": "2.848,00",
      "situation": "Pago",
      "image": "https://samsungbrshop.vtexassets.com/arquivos/ids/219667-600-auto?v=638514816133800000&width=600&height=auto&aspect=true"
    },
    {
      "id": "d824",
      "title": "Teclado Mecânico Redragon 60%",
      "value": "296,35",
      "situation": "Em aberto",
      "image": "https://imgs.casasbahia.com.br/1563739719/1xg.jpg"
    },
    {
      "title": "QCY HT05 ANC",
      "value": "279,90",
      "situation": "Em aberto",
      "image": "https://qcybrasil.com/cdn/shop/files/01_178ae03f-ac94-4916-97ec-91ff2acf3b3b.png?v=1696623815",
      "id": "fa11"
    }
  ]
}